MR_perceptual/__init__.py
MR_perceptual/test_dataset_model.py
MR_perceptual/test_network.py
MR_perceptual/data/__init__.py
MR_perceptual/data/base_data_loader.py
MR_perceptual/data/custom_dataset_data_loader.py
MR_perceptual/data/data_loader.py
MR_perceptual/data/image_folder.py
MR_perceptual/data/dataset/__init__.py
MR_perceptual/data/dataset/base_dataset.py
MR_perceptual/data/dataset/jnd_dataset.py
MR_perceptual/data/dataset/twoafc_dataset.py
MR_perceptual/mrpl/__init__.py
MR_perceptual/mrpl/mrpl.py
MR_perceptual/mrpl/pretrained_networks.py
MR_perceptual/mrpl/trainer.py
MR_perceptual/util/__init__.py
MR_perceptual/util/html.py
MR_perceptual/util/util.py
MR_perceptual/util/visualizer.py
MR_perceptual-0.1.dist-info/LICENSE
MR_perceptual-0.1.dist-info/METADATA
MR_perceptual-0.1.dist-info/WHEEL
MR_perceptual-0.1.dist-info/top_level.txt
MR_perceptual-0.1.dist-info/RECORD
